swagger_client/__init__.py
swagger_client/api_client.py
swagger_client/configuration.py
swagger_client/rest.py
swagger_client/api/__init__.py
swagger_client/api/companies_api.py
swagger_client/api/jobs_api.py
swagger_client/models/__init__.py
swagger_client/models/company.py
swagger_client/models/inline_response200.py
swagger_client/models/inline_response2001.py
swagger_client/models/job.py
test/__init__.py
test/test_companies_api.py
test/test_company.py
test/test_inline_response200.py
test/test_inline_response2001.py
test/test_job.py
test/test_jobs_api.py
vdnjobs_client-1.0.3.dist-info/METADATA
vdnjobs_client-1.0.3.dist-info/WHEEL
vdnjobs_client-1.0.3.dist-info/top_level.txt
vdnjobs_client-1.0.3.dist-info/RECORD
