Metadata-Version: 2.1
Name: vdnjobs-client
Version: 1.0.3
Summary: vdnjobs.ca Jobs API
Home-page: UNKNOWN
Author: UNKNOWN
Author-email: UNKNOWN
License: UNKNOWN
Keywords: Swagger,Jobs API
Platform: UNKNOWN
Requires-Dist: certifi (>=2017.4.17)
Requires-Dist: python-dateutil (>=2.1)
Requires-Dist: six (>=1.10)
Requires-Dist: urllib3 (>=1.23)
